[
    {
        "NAME": "GIRISH MALLYA",
        "GENDER": "M",
        "CITY": "MUMBAI",
        "STATE": "MAHARASHTRA",
        "NO. OF MARATHONS": 20,
        "STARS": "***",
        "YEAR": 2025
    },
    {
        "NAME": "HIRENDRA KURANI",
        "GENDER": "M",
        "CITY": "HENSTEDT ULZBURG",
        "STATE": "SCHLESWIG HOLSTEIN (GERMANY)",
        "NO. OF MARATHONS": 20,
        "STARS": "***",
        "YEAR": 2025
    },
    {
        "NAME": "MAHESH SALVI",
        "GENDER": "M",
        "CITY": "MUMBAI",
        "STATE": "MAHARASHTRA",
        "NO. OF MARATHONS": 20,
        "STARS": "***",
        "YEAR": 2025
    },
    {
        "NAME": "RAJ VADGAMA",
        "GENDER": "M",
        "CITY": "MUMBAI",
        "STATE": "MAHARASHTRA",
        "NO. OF MARATHONS": 20,
        "STARS": "***",
        "YEAR": 2025
    },
    {
        "NAME": "MADHUR KOTHARAY",
        "GENDER": "M",
        "CITY": "MUMBAI",
        "STATE": "MAHARASHTRA",
        "NO. OF MARATHONS": 19,
        "STARS": "**",
        "YEAR": 2025
    },
    {
        "NAME": "MUKESH SINGH",
        "GENDER": "M",
        "CITY": "BENGALURU",
        "STATE": "KARNATAKA",
        "NO. OF MARATHONS": 19,
        "STARS": "**",
        "YEAR": 2025
    },
    {
        "NAME": "KHEMRAJ VARSHNEY",
        "GENDER": "M",
        "CITY": "MUMBAI",
        "STATE": "MAHARASHTRA",
        "NO. OF MARATHONS": 18,
        "STARS": "**",
        "YEAR": 2025
    },
    {
        "NAME": "RAJESH TAGORE",
        "GENDER": "M",
        "CITY": "MUMBAI",
        "STATE": "MAHARASHTRA",
        "NO. OF MARATHONS": 18,
        "STARS": "**",
        "YEAR": 2025
    },
    {
        "NAME": "BHASKER SHARMA",
        "GENDER": "M",
        "CITY": "BENGALURU",
        "STATE": "KARNATAKA",
        "NO. OF MARATHONS": 17,
        "STARS": "**",
        "YEAR": 2025
    },
    {
        "NAME": "SHEETAL MOHITE",
        "GENDER": "M",
        "CITY": "MUMBAI",
        "STATE": "MAHARASHTRA",
        "NO. OF MARATHONS": 17,
        "STARS": "**",
        "YEAR": 2025
    },
    {
        "NAME": "AMIT SHETH",
        "GENDER": "M",
        "CITY": "MUMBAI",
        "STATE": "MAHARASHTRA",
        "NO. OF MARATHONS": 16,
        "STARS": "**",
        "YEAR": 2025
    },
    {
        "NAME": "ASHOK NATH",
        "GENDER": "M",
        "CITY": "BENGALURU",
        "STATE": "KARNATAKA",
        "NO. OF MARATHONS": 16,
        "STARS": "**",
        "YEAR": 2025
    },
    {
        "NAME": "BIREN JALUI",
        "GENDER": "M",
        "CITY": "MUMBAI",
        "STATE": "MAHARASHTRA",
        "NO. OF MARATHONS": 16,
        "STARS": "**",
        "YEAR": 2025
    },
    {
        "NAME": "CYRUS PALSETIA",
        "GENDER": "M",
        "CITY": "VADODARA",
        "STATE": "GUJARAT",
        "NO. OF MARATHONS": 16,
        "STARS": "**",
        "YEAR": 2025
    },
    {
        "NAME": "DHARMENDRA D",
        "GENDER": "M",
        "CITY": "BENGALURU",
        "STATE": "KARNATAKA",
        "NO. OF MARATHONS": 16,
        "STARS": "**",
        "YEAR": 2025
    },
    {
        "NAME": "DURGESH KASHYAP",
        "GENDER": "M",
        "CITY": "MUMBAI",
        "STATE": "MAHARASHTRA",
        "NO. OF MARATHONS": 16,
        "STARS": "**",
        "YEAR": 2025
    },
    {
        "NAME": "MADHUSOODANAN NAIR",
        "GENDER": "M",
        "CITY": "MUMBAI",
        "STATE": "MAHARASHTRA",
        "NO. OF MARATHONS": 16,
        "STARS": "**",
        "YEAR": 2025
    },
    {
        "NAME": "NEEPA SHETH",
        "GENDER": "F",
        "CITY": "MUMBAI",
        "STATE": "MAHARASHTRA",
        "NO. OF MARATHONS": 16,
        "STARS": "**",
        "YEAR": 2025
    },
    {
        "NAME": "PANKAJ SHARMA",
        "GENDER": "M",
        "CITY": "MUMBAI",
        "STATE": "MAHARASHTRA",
        "NO. OF MARATHONS": 16,
        "STARS": "**",
        "YEAR": 2025
    },
    {
        "NAME": "RAMANI BRAHMA",
        "GENDER": "M",
        "CITY": "THANE",
        "STATE": "MAHARASHTRA",
        "NO. OF MARATHONS": 16,
        "STARS": "**",
        "YEAR": 2025
    },
    {
        "NAME": "VARUN JOSHI",
        "GENDER": "M",
        "CITY": "THANE",
        "STATE": "MAHARASHTRA",
        "NO. OF MARATHONS": 16,
        "STARS": "**",
        "YEAR": 2025
    },
    {
        "NAME": "VENKATESAN KRISHNASWAMI",
        "GENDER": "M",
        "CITY": "SRIRANGAM",
        "STATE": "TAMIL NADU",
        "NO. OF MARATHONS": 16,
        "STARS": "**",
        "YEAR": 2025
    },
    {
        "NAME": "AJIT DEDHIA",
        "GENDER": "M",
        "CITY": "MUMBAI",
        "STATE": "MAHARASHTRA",
        "NO. OF MARATHONS": 15,
        "STARS": "**",
        "YEAR": 2025
    },
    {
        "NAME": "ASIF CHAUS",
        "GENDER": "M",
        "CITY": "MUMBAI",
        "STATE": "MAHARASHTRA",
        "NO. OF MARATHONS": 15,
        "STARS": "**",
        "YEAR": 2025
    },
    {
        "NAME": "LYNDON SOARES",
        "GENDER": "M",
        "CITY": "MUMBAI",
        "STATE": "MAHARASHTRA",
        "NO. OF MARATHONS": 15,
        "STARS": "**",
        "YEAR": 2025
    },
    {
        "NAME": "MAKARAND KAMAT",
        "GENDER": "M",
        "CITY": "MUMBAI",
        "STATE": "MAHARASHTRA",
        "NO. OF MARATHONS": 15,
        "STARS": "**",
        "YEAR": 2025
    },
    {
        "NAME": "SHASHANK KAMAT",
        "GENDER": "M",
        "CITY": "MUMBAI",
        "STATE": "MAHARASHTRA",
        "NO. OF MARATHONS": 15,
        "STARS": "**",
        "YEAR": 2025
    },
    {
        "NAME": "SRINIVAS RAMANUJAM",
        "GENDER": "M",
        "CITY": "BENGALURU",
        "STATE": "KARNATAKA",
        "NO. OF MARATHONS": 15,
        "STARS": "**",
        "YEAR": 2025
    },
    {
        "NAME": "SUDHANSHU VATS",
        "GENDER": "M",
        "CITY": "MUMBAI",
        "STATE": "MAHARASHTRA",
        "NO. OF MARATHONS": 15,
        "STARS": "**",
        "YEAR": 2025
    },
    {
        "NAME": "SUNIL RAMDAS LAHIGUDE",
        "GENDER": "M",
        "CITY": "MUMBAI",
        "STATE": "MAHARASHTRA",
        "NO. OF MARATHONS": 15,
        "STARS": "**",
        "YEAR": 2025
    },
    {
        "NAME": "SURESH NEGI",
        "GENDER": "M",
        "CITY": "MUMBAI",
        "STATE": "MAHARASHTRA",
        "NO. OF MARATHONS": 15,
        "STARS": "**",
        "YEAR": 2025
    },
    {
        "NAME": "ABHIJIT SHOME",
        "GENDER": "M",
        "CITY": "MUMBAI",
        "STATE": "MAHARASHTRA",
        "NO. OF MARATHONS": 14,
        "STARS": "*",
        "YEAR": 2025
    },
    {
        "NAME": "AJIT OAK",
        "GENDER": "M",
        "CITY": "THANE",
        "STATE": "MAHARASHTRA",
        "NO. OF MARATHONS": 14,
        "STARS": "*",
        "YEAR": 2025
    },
    {
        "NAME": "CAPT MAHESH JOG",
        "GENDER": "M",
        "CITY": "PUNE",
        "STATE": "MAHARASHTRA",
        "NO. OF MARATHONS": 14,
        "STARS": "*",
        "YEAR": 2025
    },
    {
        "NAME": "CHANDRA KUMAR",
        "GENDER": "M",
        "CITY": "BENGALURU",
        "STATE": "KARNATAKA",
        "NO. OF MARATHONS": 14,
        "STARS": "*",
        "YEAR": 2025
    },
    {
        "NAME": "CHANDRAMOHAN BHATT",
        "GENDER": "M",
        "CITY": "MUMBAI",
        "STATE": "MAHARASHTRA",
        "NO. OF MARATHONS": 14,
        "STARS": "*",
        "YEAR": 2025
    },
    {
        "NAME": "CYRUS MEHTA",
        "GENDER": "M",
        "CITY": "MUMBAI",
        "STATE": "MAHARASHTRA",
        "NO. OF MARATHONS": 14,
        "STARS": "*",
        "YEAR": 2025
    },
    {
        "NAME": "GEORGE VARGHESE",
        "GENDER": "M",
        "CITY": "ERNAKULAM",
        "STATE": "KERALA",
        "NO. OF MARATHONS": 14,
        "STARS": "*",
        "YEAR": 2025
    },
    {
        "NAME": "KISHLAY VATSYAYAN",
        "GENDER": "M",
        "CITY": "GHAZIABAD",
        "STATE": "UTTAR PRADESH",
        "NO. OF MARATHONS": 14,
        "STARS": "*",
        "YEAR": 2025
    },
    {
        "NAME": "NIXON JOSEPH",
        "GENDER": "M",
        "CITY": "BENGALURU",
        "STATE": "KARNATAKA",
        "NO. OF MARATHONS": 14,
        "STARS": "*",
        "YEAR": 2025
    },
    {
        "NAME": "RAJENDRA BHUJBAL",
        "GENDER": "M",
        "CITY": "MUMBAI",
        "STATE": "MAHARASHTRA",
        "NO. OF MARATHONS": 14,
        "STARS": "*",
        "YEAR": 2025
    },
    {
        "NAME": "RAMASWAMY NARAYANAN",
        "GENDER": "M",
        "CITY": "BENGALURU",
        "STATE": "KARNATAKA",
        "NO. OF MARATHONS": 14,
        "STARS": "*",
        "YEAR": 2025
    },
    {
        "NAME": "SANTOSH TANDON",
        "GENDER": "M",
        "CITY": "MUMBAI",
        "STATE": "MAHARASHTRA",
        "NO. OF MARATHONS": 14,
        "STARS": "*",
        "YEAR": 2025
    },
    {
        "NAME": "SRINIVAS GUNTUPALLI",
        "GENDER": "M",
        "CITY": "BENGALURU",
        "STATE": "KARNATAKA",
        "NO. OF MARATHONS": 14,
        "STARS": "*",
        "YEAR": 2025
    },
    {
        "NAME": "VIJAY RAMAKRISHNAN",
        "GENDER": "M",
        "CITY": "MUMBAI",
        "STATE": "MAHARASHTRA",
        "NO. OF MARATHONS": 14,
        "STARS": "*",
        "YEAR": 2025
    },
    {
        "NAME": "VINEETA SINGH",
        "GENDER": "F",
        "CITY": "MUMBAI",
        "STATE": "MAHARASHTRA",
        "NO. OF MARATHONS": 14,
        "STARS": "*",
        "YEAR": 2025
    },
    {
        "NAME": "AMBARISH GURAV",
        "GENDER": "M",
        "CITY": "MUMBAI",
        "STATE": "MAHARASHTRA",
        "NO. OF MARATHONS": 13,
        "STARS": "*",
        "YEAR": 2025
    },
    {
        "NAME": "ARJUN JOSHI",
        "GENDER": "M",
        "CITY": "NEW DELHI",
        "STATE": "DELHI",
        "NO. OF MARATHONS": 13,
        "STARS": "*",
        "YEAR": 2025
    },
    {
        "NAME": "BHUPENDRA SHAH",
        "GENDER": "M",
        "CITY": "MUMBAI",
        "STATE": "MAHARASHTRA",
        "NO. OF MARATHONS": 13,
        "STARS": "*",
        "YEAR": 2025
    },
    {
        "NAME": "DEVESH KHATU",
        "GENDER": "M",
        "CITY": "MUMBAI",
        "STATE": "MAHARASHTRA",
        "NO. OF MARATHONS": 13,
        "STARS": "*",
        "YEAR": 2025
    },
    {
        "NAME": "DILIP PATIL",
        "GENDER": "M",
        "CITY": "MUMBAI",
        "STATE": "MAHARASHTRA",
        "NO. OF MARATHONS": 13,
        "STARS": "*",
        "YEAR": 2025
    },
    {
        "NAME": "DNYANESHWAR TIDKE",
        "GENDER": "M",
        "CITY": "NAVI MUMBAI",
        "STATE": "MAHARASHTRA",
        "NO. OF MARATHONS": 13,
        "STARS": "*",
        "YEAR": 2025
    },
    {
        "NAME": "DRAYTON ALMEIDA",
        "GENDER": "M",
        "CITY": "MUMBAI",
        "STATE": "MAHARASHTRA",
        "NO. OF MARATHONS": 13,
        "STARS": "*",
        "YEAR": 2025
    },
    {
        "NAME": "JAYANT KANSARA",
        "GENDER": "M",
        "CITY": "NASHIK",
        "STATE": "MAHARASHTRA",
        "NO. OF MARATHONS": 13,
        "STARS": "*",
        "YEAR": 2025
    },
    {
        "NAME": "JIGNESH BARASARA",
        "GENDER": "M",
        "CITY": "MUMBAI",
        "STATE": "MAHARASHTRA",
        "NO. OF MARATHONS": 13,
        "STARS": "*",
        "YEAR": 2025
    },
    {
        "NAME": "KAVIN KONDABATHINI",
        "GENDER": "M",
        "CITY": "MUMBAI",
        "STATE": "MAHARASHTRA",
        "NO. OF MARATHONS": 13,
        "STARS": "*",
        "YEAR": 2025
    },
    {
        "NAME": "MANJUNATH NAYAK",
        "GENDER": "M",
        "CITY": "MANGALURU",
        "STATE": "KARNATAKA",
        "NO. OF MARATHONS": 13,
        "STARS": "*",
        "YEAR": 2025
    },
    {
        "NAME": "MAYUR BHAT",
        "GENDER": "M",
        "CITY": "MUMBAI",
        "STATE": "MAHARASHTRA",
        "NO. OF MARATHONS": 13,
        "STARS": "*",
        "YEAR": 2025
    },
    {
        "NAME": "MURALIDHAR NANNAPANENI",
        "GENDER": "M",
        "CITY": "HYDERABAD",
        "STATE": "TELANGANA",
        "NO. OF MARATHONS": 13,
        "STARS": "*",
        "YEAR": 2025
    },
    {
        "NAME": "NARASIMHAN S R",
        "GENDER": "M",
        "CITY": "GURGAON",
        "STATE": "HARYANA",
        "NO. OF MARATHONS": 13,
        "STARS": "*",
        "YEAR": 2025
    },
    {
        "NAME": "PARMESH OHRI",
        "GENDER": "M",
        "CITY": "MUMBAI",
        "STATE": "MAHARASHTRA",
        "NO. OF MARATHONS": 13,
        "STARS": "*",
        "YEAR": 2025
    },
    {
        "NAME": "PRAKASH POOJARY",
        "GENDER": "M",
        "CITY": "NAVI MUMBAI",
        "STATE": "MAHARASHTRA",
        "NO. OF MARATHONS": 13,
        "STARS": "*",
        "YEAR": 2025
    },
    {
        "NAME": "PRASHANT MODY",
        "GENDER": "M",
        "CITY": "MUMBAI",
        "STATE": "MAHARASHTRA",
        "NO. OF MARATHONS": 13,
        "STARS": "*",
        "YEAR": 2025
    },
    {
        "NAME": "PRATUL VARSHNEY",
        "GENDER": "M",
        "CITY": "BENGALURU",
        "STATE": "KARNATAKA",
        "NO. OF MARATHONS": 13,
        "STARS": "*",
        "YEAR": 2025
    },
    {
        "NAME": "RAHUL VERGHESE",
        "GENDER": "M",
        "CITY": "SINGAPORE",
        "STATE": "SINGAPORE",
        "NO. OF MARATHONS": 13,
        "STARS": "*",
        "YEAR": 2025
    },
    {
        "NAME": "RAJU BHADKE",
        "GENDER": "M",
        "CITY": "MUMBAI",
        "STATE": "MAHARASHTRA",
        "NO. OF MARATHONS": 13,
        "STARS": "*",
        "YEAR": 2025
    },
    {
        "NAME": "RUPESH SATNALIWALA",
        "GENDER": "M",
        "CITY": "MUMBAI",
        "STATE": "MAHARASHTRA",
        "NO. OF MARATHONS": 13,
        "STARS": "*",
        "YEAR": 2025
    },
    {
        "NAME": "SHANKAR WABLE",
        "GENDER": "M",
        "CITY": "PUNE",
        "STATE": "MAHARASHTRA",
        "NO. OF MARATHONS": 13,
        "STARS": "*",
        "YEAR": 2025
    },
    {
        "NAME": "SUMIL RASTOGI",
        "GENDER": "M",
        "CITY": "MUMBAI",
        "STATE": "MAHARASHTRA",
        "NO. OF MARATHONS": 13,
        "STARS": "*",
        "YEAR": 2025
    },
    {
        "NAME": "SUNIL CHAINANI",
        "GENDER": "M",
        "CITY": "BENGALURU",
        "STATE": "KARNATAKA",
        "NO. OF MARATHONS": 13,
        "STARS": "*",
        "YEAR": 2025
    },
    {
        "NAME": "SUNIL KUMAR",
        "GENDER": "M",
        "CITY": "THANE",
        "STATE": "MAHARASHTRA",
        "NO. OF MARATHONS": 13,
        "STARS": "*",
        "YEAR": 2025
    },
    {
        "NAME": "SURAJ SUVARNA",
        "GENDER": "M",
        "CITY": "THANE",
        "STATE": "MAHARASHTRA",
        "NO. OF MARATHONS": 13,
        "STARS": "*",
        "YEAR": 2025
    },
    {
        "NAME": "THOMAS PHILIP",
        "GENDER": "M",
        "CITY": "BENGALURU",
        "STATE": "KARNATAKA",
        "NO. OF MARATHONS": 13,
        "STARS": "*",
        "YEAR": 2025
    },
    {
        "NAME": "UDAY BOBHATE",
        "GENDER": "M",
        "CITY": "MUMBAI",
        "STATE": "MAHARASHTRA",
        "NO. OF MARATHONS": 13,
        "STARS": "*",
        "YEAR": 2025
    },
    {
        "NAME": "VASANT PINGALE",
        "GENDER": "M",
        "CITY": "MUMBAI",
        "STATE": "MAHARASHTRA",
        "NO. OF MARATHONS": 13,
        "STARS": "*",
        "YEAR": 2025
    },
    {
        "NAME": "VENKATARAMAN G S",
        "GENDER": "M",
        "CITY": "BENGALURU",
        "STATE": "KARNATAKA",
        "NO. OF MARATHONS": 13,
        "STARS": "*",
        "YEAR": 2025
    },
    {
        "NAME": "AADESH MORE",
        "GENDER": "M",
        "CITY": "MUMBAI",
        "STATE": "MAHARASHTRA",
        "NO. OF MARATHONS": 12,
        "STARS": "*",
        "YEAR": 2025
    },
    {
        "NAME": "AKSHAY KAPUR",
        "GENDER": "M",
        "CITY": "MUMBAI",
        "STATE": "MAHARASHTRA",
        "NO. OF MARATHONS": 12,
        "STARS": "*",
        "YEAR": 2025
    },
    {
        "NAME": "AMIT AHUJA",
        "GENDER": "M",
        "CITY": "THANE",
        "STATE": "MAHARASHTRA",
        "NO. OF MARATHONS": 12,
        "STARS": "*",
        "YEAR": 2025
    },
    {
        "NAME": "ANAND SINGH",
        "GENDER": "M",
        "CITY": "MUMBAI",
        "STATE": "MAHARASHTRA",
        "NO. OF MARATHONS": 12,
        "STARS": "*",
        "YEAR": 2025
    },
    {
        "NAME": "ARUN PRASAD",
        "GENDER": "M",
        "CITY": "BENGALURU",
        "STATE": "KARNATAKA",
        "NO. OF MARATHONS": 12,
        "STARS": "*",
        "YEAR": 2025
    },
    {
        "NAME": "ASHOK CHAWLA",
        "GENDER": "M",
        "CITY": "MUMBAI",
        "STATE": "MAHARASHTRA",
        "NO. OF MARATHONS": 12,
        "STARS": "*",
        "YEAR": 2025
    },
    {
        "NAME": "ASHOK JOSHI",
        "GENDER": "M",
        "CITY": "PUNE",
        "STATE": "MAHARASHTRA",
        "NO. OF MARATHONS": 12,
        "STARS": "*",
        "YEAR": 2025
    },
    {
        "NAME": "ATUL VAIDYA",
        "GENDER": "M",
        "CITY": "MUMBAI",
        "STATE": "MAHARASHTRA",
        "NO. OF MARATHONS": 12,
        "STARS": "*",
        "YEAR": 2025
    },
    {
        "NAME": "BALAJI V V",
        "GENDER": "M",
        "CITY": "MUMBAI",
        "STATE": "MAHARASHTRA",
        "NO. OF MARATHONS": 12,
        "STARS": "*",
        "YEAR": 2025
    },
    {
        "NAME": "CHINMAY HALANKAR",
        "GENDER": "M",
        "CITY": "MUMBAI",
        "STATE": "MAHARASHTRA",
        "NO. OF MARATHONS": 12,
        "STARS": "*",
        "YEAR": 2025
    },
    {
        "NAME": "DEVENDRA TANDEL",
        "GENDER": "M",
        "CITY": "MUMBAI",
        "STATE": "MAHARASHTRA",
        "NO. OF MARATHONS": 12,
        "STARS": "*",
        "YEAR": 2025
    },
    {
        "NAME": "GEORGE JOSEPH",
        "GENDER": "M",
        "CITY": "KOCHI",
        "STATE": "KERALA",
        "NO. OF MARATHONS": 12,
        "STARS": "*",
        "YEAR": 2025
    },
    {
        "NAME": "GIRISH SHIRODKAR",
        "GENDER": "M",
        "CITY": "MUMBAI",
        "STATE": "MAHARASHTRA",
        "NO. OF MARATHONS": 12,
        "STARS": "*",
        "YEAR": 2025
    },
    {
        "NAME": "KEYUR KAPADIA",
        "GENDER": "M",
        "CITY": "MUMBAI",
        "STATE": "MAHARASHTRA",
        "NO. OF MARATHONS": 12,
        "STARS": "*",
        "YEAR": 2025
    },
    {
        "NAME": "KIRAN SOLANKI",
        "GENDER": "M",
        "CITY": "MUMBAI",
        "STATE": "MAHARASHTRA",
        "NO. OF MARATHONS": 12,
        "STARS": "*",
        "YEAR": 2025
    },
    {
        "NAME": "KOTHANDAPANI K C",
        "GENDER": "M",
        "CITY": "BENGALURU",
        "STATE": "KARNATAKA",
        "NO. OF MARATHONS": 12,
        "STARS": "*",
        "YEAR": 2025
    },
    {
        "NAME": "KRISH SHANKAR",
        "GENDER": "M",
        "CITY": "MUMBAI",
        "STATE": "MAHARASHTRA",
        "NO. OF MARATHONS": 12,
        "STARS": "*",
        "YEAR": 2025
    },
    {
        "NAME": "MAHESH NAGWEKAR",
        "GENDER": "M",
        "CITY": "MUMBAI",
        "STATE": "MAHARASHTRA",
        "NO. OF MARATHONS": 12,
        "STARS": "*",
        "YEAR": 2025
    },
    {
        "NAME": "MAHIPAL JAIN",
        "GENDER": "M",
        "CITY": "MUMBAI",
        "STATE": "MAHARASHTRA",
        "NO. OF MARATHONS": 12,
        "STARS": "*",
        "YEAR": 2025
    },
    {
        "NAME": "MAKARAND DESHPANDE",
        "GENDER": "M",
        "CITY": "MUMBAI",
        "STATE": "MAHARASHTRA",
        "NO. OF MARATHONS": 12,
        "STARS": "*",
        "YEAR": 2025
    },
    {
        "NAME": "MILIND SOMAN",
        "GENDER": "M",
        "CITY": "MUMBAI",
        "STATE": "MAHARASHTRA",
        "NO. OF MARATHONS": 12,
        "STARS": "*",
        "YEAR": 2025
    },
    {
        "NAME": "MUNIR KULAVOOR",
        "GENDER": "M",
        "CITY": "MUMBAI",
        "STATE": "MAHARASHTRA",
        "NO. OF MARATHONS": 12,
        "STARS": "*",
        "YEAR": 2025
    },
    {
        "NAME": "NAGESH KAMAT",
        "GENDER": "M",
        "CITY": "VADODARA",
        "STATE": "GUJARAT",
        "NO. OF MARATHONS": 12,
        "STARS": "*",
        "YEAR": 2025
    },
    {
        "NAME": "NAVIN KUMAR",
        "GENDER": "M",
        "CITY": "BENGALURU",
        "STATE": "KARNATAKA",
        "NO. OF MARATHONS": 12,
        "STARS": "*",
        "YEAR": 2025
    },
    {
        "NAME": "NITESH TRIVEDI",
        "GENDER": "M",
        "CITY": "NAVI MUMBAI",
        "STATE": "MAHARASHTRA",
        "NO. OF MARATHONS": 12,
        "STARS": "*",
        "YEAR": 2025
    },
    {
        "NAME": "OMPRAKASH MANDLEKAR",
        "GENDER": "M",
        "CITY": "MUMBAI",
        "STATE": "MAHARASHTRA",
        "NO. OF MARATHONS": 12,
        "STARS": "*",
        "YEAR": 2025
    },
    {
        "NAME": "PANKAJ RAI",
        "GENDER": "M",
        "CITY": "BENGALURU",
        "STATE": "KARNATAKA",
        "NO. OF MARATHONS": 12,
        "STARS": "*",
        "YEAR": 2025
    },
    {
        "NAME": "PRABHAKAR KOLI",
        "GENDER": "M",
        "CITY": "MUMBAI",
        "STATE": "MAHARASHTRA",
        "NO. OF MARATHONS": 12,
        "STARS": "*",
        "YEAR": 2025
    },
    {
        "NAME": "RAHUL AGRAWAL",
        "GENDER": "M",
        "CITY": "THANE",
        "STATE": "MAHARASHTRA",
        "NO. OF MARATHONS": 12,
        "STARS": "*",
        "YEAR": 2025
    },
    {
        "NAME": "RAHUL VAIDYA",
        "GENDER": "M",
        "CITY": "MUMBAI",
        "STATE": "MAHARASHTRA",
        "NO. OF MARATHONS": 12,
        "STARS": "*",
        "YEAR": 2025
    },
    {
        "NAME": "RAMDAS PULAPAKA",
        "GENDER": "M",
        "CITY": "MUMBAI",
        "STATE": "MAHARASHTRA",
        "NO. OF MARATHONS": 12,
        "STARS": "*",
        "YEAR": 2025
    },
    {
        "NAME": "RISHIKESH BASU",
        "GENDER": "M",
        "CITY": "BENGALURU",
        "STATE": "KARNATAKA",
        "NO. OF MARATHONS": 12,
        "STARS": "*",
        "YEAR": 2025
    },
    {
        "NAME": "ROHIT BANSAL",
        "GENDER": "M",
        "CITY": "JAIPUR",
        "STATE": "RAJASTHAN",
        "NO. OF MARATHONS": 12,
        "STARS": "*",
        "YEAR": 2025
    },
    {
        "NAME": "RUPESH PRABHUNERURKAR",
        "GENDER": "M",
        "CITY": "MUMBAI",
        "STATE": "MAHARASHTRA",
        "NO. OF MARATHONS": 12,
        "STARS": "*",
        "YEAR": 2025
    },
    {
        "NAME": "SACHIN PUNTAMBEKAR",
        "GENDER": "M",
        "CITY": "MUMBAI",
        "STATE": "MAHARASHTRA",
        "NO. OF MARATHONS": 12,
        "STARS": "*",
        "YEAR": 2025
    },
    {
        "NAME": "SANJAI BANERJI",
        "GENDER": "M",
        "CITY": "SATNA",
        "STATE": "\"MADHYA PRADESH",
        "NO. OF MARATHONS": null,
        "STARS": "",
        "YEAR": 2025
    },
    {
        "NAME": "\"",
        "GENDER": "12",
        "CITY": "*",
        "STATE": "",
        "NO. OF MARATHONS": null,
        "STARS": "",
        "YEAR": 2025
    },
    {
        "NAME": "SANTHOSH SRINIVASAN",
        "GENDER": "M",
        "CITY": "TAMBARAM",
        "STATE": "TAMIL NADU",
        "NO. OF MARATHONS": 12,
        "STARS": "*",
        "YEAR": 2025
    },
    {
        "NAME": "SATYASESHASAI CASUKHELA",
        "GENDER": "M",
        "CITY": "BENGALURU",
        "STATE": "KARNATAKA",
        "NO. OF MARATHONS": 12,
        "STARS": "*",
        "YEAR": 2025
    },
    {
        "NAME": "SHYAM LATA",
        "GENDER": "M",
        "CITY": "MUMBAI",
        "STATE": "MAHARASHTRA",
        "NO. OF MARATHONS": 12,
        "STARS": "*",
        "YEAR": 2025
    },
    {
        "NAME": "SRIKRISHNA DWARAM",
        "GENDER": "M",
        "CITY": "MUMBAI",
        "STATE": "MAHARASHTRA",
        "NO. OF MARATHONS": 12,
        "STARS": "*",
        "YEAR": 2025
    },
    {
        "NAME": "SUVASHCHANDRA SHUKLA",
        "GENDER": "M",
        "CITY": "MUMBAI",
        "STATE": "MAHARASHTRA",
        "NO. OF MARATHONS": 12,
        "STARS": "*",
        "YEAR": 2025
    },
    {
        "NAME": "UMESH SONAVANE",
        "GENDER": "M",
        "CITY": "PIMPRI",
        "STATE": "MAHARASHTRA",
        "NO. OF MARATHONS": 12,
        "STARS": "*",
        "YEAR": 2025
    },
    {
        "NAME": "VENKATARAMANI RAMIAH",
        "GENDER": "M",
        "CITY": "CHENNAI",
        "STATE": "TAMIL NADU",
        "NO. OF MARATHONS": 12,
        "STARS": "*",
        "YEAR": 2025
    },
    {
        "NAME": "VIKRANT PATIL",
        "GENDER": "M",
        "CITY": "MUMBAI",
        "STATE": "MAHARASHTRA",
        "NO. OF MARATHONS": 12,
        "STARS": "*",
        "YEAR": 2025
    },
    {
        "NAME": "VISHAL BHANSALI",
        "GENDER": "M",
        "CITY": "MUMBAI",
        "STATE": "MAHARASHTRA",
        "NO. OF MARATHONS": 12,
        "STARS": "*",
        "YEAR": 2025
    },
    {
        "NAME": "ALOK KUMAR",
        "GENDER": "M",
        "CITY": "NAVI MUMBAI",
        "STATE": "MAHARASHTRA",
        "NO. OF MARATHONS": 11,
        "STARS": "*",
        "YEAR": 2025
    },
    {
        "NAME": "AMIT OJHA",
        "GENDER": "M",
        "CITY": "NEW DELHI",
        "STATE": "DELHI",
        "NO. OF MARATHONS": 11,
        "STARS": "*",
        "YEAR": 2025
    },
    {
        "NAME": "ANKIT DAS",
        "GENDER": "M",
        "CITY": "MUMBAI",
        "STATE": "MAHARASHTRA",
        "NO. OF MARATHONS": 11,
        "STARS": "*",
        "YEAR": 2025
    },
    {
        "NAME": "APARNA CHOUDHARY",
        "GENDER": "F",
        "CITY": "GURGAON",
        "STATE": "HARYANA",
        "NO. OF MARATHONS": 11,
        "STARS": "*",
        "YEAR": 2025
    },
    {
        "NAME": "ASHOK KHANVTE",
        "GENDER": "M",
        "CITY": "MUMBAI",
        "STATE": "MAHARASHTRA",
        "NO. OF MARATHONS": 11,
        "STARS": "*",
        "YEAR": 2025
    },
    {
        "NAME": "ASHWIN KUMAR BAKSHI",
        "GENDER": "M",
        "CITY": "NAVI MUMBAI",
        "STATE": "MAHARASHTRA",
        "NO. OF MARATHONS": 11,
        "STARS": "*",
        "YEAR": 2025
    },
    {
        "NAME": "AVINASH MANE",
        "GENDER": "M",
        "CITY": "PUNE",
        "STATE": "MAHARASHTRA",
        "NO. OF MARATHONS": 11,
        "STARS": "*",
        "YEAR": 2025
    },
    {
        "NAME": "BIJAY NAIR",
        "GENDER": "M",
        "CITY": "MUMBAI",
        "STATE": "MAHARASHTRA",
        "NO. OF MARATHONS": 11,
        "STARS": "*",
        "YEAR": 2025
    },
    {
        "NAME": "BIRBAL SAWAIYAN",
        "GENDER": "M",
        "CITY": "MUMBAI",
        "STATE": "MAHARASHTRA",
        "NO. OF MARATHONS": 11,
        "STARS": "*",
        "YEAR": 2025
    },
    {
        "NAME": "BRIJ MOHAN SHARMA",
        "GENDER": "M",
        "CITY": "MUMBAI",
        "STATE": "MAHARASHTRA",
        "NO. OF MARATHONS": 11,
        "STARS": "*",
        "YEAR": 2025
    },
    {
        "NAME": "CAPT SWAMINATHAN IYER",
        "GENDER": "M",
        "CITY": "MUMBAI",
        "STATE": "MAHARASHTRA",
        "NO. OF MARATHONS": 11,
        "STARS": "*",
        "YEAR": 2025
    },
    {
        "NAME": "CHARUSHEELA DESHMUKH",
        "GENDER": "F",
        "CITY": "CHHATRAPATI SAMBHAJI NAGAR",
        "STATE": "MAHARASHTRA",
        "NO. OF MARATHONS": 11,
        "STARS": "*",
        "YEAR": 2025
    },
    {
        "NAME": "DANIEL VAZ",
        "GENDER": "M",
        "CITY": "MUMBAI",
        "STATE": "MAHARASHTRA",
        "NO. OF MARATHONS": 11,
        "STARS": "*",
        "YEAR": 2025
    },
    {
        "NAME": "DEEPAK MHASAVADE",
        "GENDER": "M",
        "CITY": "BENGALURU",
        "STATE": "KARNATAKA",
        "NO. OF MARATHONS": 11,
        "STARS": "*",
        "YEAR": 2025
    },
    {
        "NAME": "DEVENDRA KISHORE PRASAD",
        "GENDER": "M",
        "CITY": "GHAZIABAD",
        "STATE": "UTTAR PRADESH",
        "NO. OF MARATHONS": 11,
        "STARS": "*",
        "YEAR": 2025
    },
    {
        "NAME": "DINESH HEDA",
        "GENDER": "M",
        "CITY": "DABOLIM",
        "STATE": "GOA",
        "NO. OF MARATHONS": 11,
        "STARS": "*",
        "YEAR": 2025
    },
    {
        "NAME": "GANESH IYER",
        "GENDER": "M",
        "CITY": "MUMBAI",
        "STATE": "MAHARASHTRA",
        "NO. OF MARATHONS": 11,
        "STARS": "*",
        "YEAR": 2025
    },
    {
        "NAME": "GERALD PDE",
        "GENDER": "M",
        "CITY": "SHILLONG",
        "STATE": "MEGHALAYA",
        "NO. OF MARATHONS": 11,
        "STARS": "*",
        "YEAR": 2025
    },
    {
        "NAME": "HARSHA VARDHAN",
        "GENDER": "M",
        "CITY": "MUMBAI",
        "STATE": "MAHARASHTRA",
        "NO. OF MARATHONS": 11,
        "STARS": "*",
        "YEAR": 2025
    },
    {
        "NAME": "HIMANSHU VINCHHI",
        "GENDER": "M",
        "CITY": "MUMBAI",
        "STATE": "MAHARASHTRA",
        "NO. OF MARATHONS": 11,
        "STARS": "*",
        "YEAR": 2025
    },
    {
        "NAME": "INDRANEEL GHOSE",
        "GENDER": "M",
        "CITY": "NOIDA",
        "STATE": "UTTAR PRADESH",
        "NO. OF MARATHONS": 11,
        "STARS": "*",
        "YEAR": 2025
    },
    {
        "NAME": "JAIPRAKASH VAISHYA",
        "GENDER": "M",
        "CITY": "MUMBAI",
        "STATE": "MAHARASHTRA",
        "NO. OF MARATHONS": 11,
        "STARS": "*",
        "YEAR": 2025
    },
    {
        "NAME": "JOGESH PRAJAPATI",
        "GENDER": "M",
        "CITY": "MUMBAI",
        "STATE": "MAHARASHTRA",
        "NO. OF MARATHONS": 11,
        "STARS": "*",
        "YEAR": 2025
    },
    {
        "NAME": "JOTHI PADMANABHAN",
        "GENDER": "M",
        "CITY": "BENGALURU",
        "STATE": "KARNATAKA",
        "NO. OF MARATHONS": 11,
        "STARS": "*",
        "YEAR": 2025
    },
    {
        "NAME": "KAILASH CHAND JOSHI",
        "GENDER": "M",
        "CITY": "NEW DELHI",
        "STATE": "DELHI",
        "NO. OF MARATHONS": 11,
        "STARS": "*",
        "YEAR": 2025
    },
    {
        "NAME": "KALPESH PATEL",
        "GENDER": "M",
        "CITY": "MUMBAI",
        "STATE": "MAHARASHTRA",
        "NO. OF MARATHONS": 11,
        "STARS": "*",
        "YEAR": 2025
    },
    {
        "NAME": "KAPIL VIJ",
        "GENDER": "M",
        "CITY": "MUMBAI",
        "STATE": "MAHARASHTRA",
        "NO. OF MARATHONS": 11,
        "STARS": "*",
        "YEAR": 2025
    },
    {
        "NAME": "KAUSHIK PANCHAL",
        "GENDER": "M",
        "CITY": "MUMBAI",
        "STATE": "MAHARASHTRA",
        "NO. OF MARATHONS": 11,
        "STARS": "*",
        "YEAR": 2025
    },
    {
        "NAME": "KEVAN GANDHI",
        "GENDER": "M",
        "CITY": "MUMBAI",
        "STATE": "MAHARASHTRA",
        "NO. OF MARATHONS": 11,
        "STARS": "*",
        "YEAR": 2025
    },
    {
        "NAME": "KHUSHBOO VAISH",
        "GENDER": "F",
        "CITY": "MUMBAI",
        "STATE": "MAHARASHTRA",
        "NO. OF MARATHONS": 11,
        "STARS": "*",
        "YEAR": 2025
    },
    {
        "NAME": "KRANTI SALVI",
        "GENDER": "F",
        "CITY": "MUMBAI",
        "STATE": "MAHARASHTRA",
        "NO. OF MARATHONS": 11,
        "STARS": "*",
        "YEAR": 2025
    },
    {
        "NAME": "MAHESH MHATRE",
        "GENDER": "M",
        "CITY": "MUMBAI",
        "STATE": "MAHARASHTRA",
        "NO. OF MARATHONS": 11,
        "STARS": "*",
        "YEAR": 2025
    },
    {
        "NAME": "MAKARAND LELE",
        "GENDER": "M",
        "CITY": "VADODARA",
        "STATE": "GUJARAT",
        "NO. OF MARATHONS": 11,
        "STARS": "*",
        "YEAR": 2025
    },
    {
        "NAME": "MALAY GHOSH",
        "GENDER": "M",
        "CITY": "MUMBAI",
        "STATE": "MAHARASHTRA",
        "NO. OF MARATHONS": 11,
        "STARS": "*",
        "YEAR": 2025
    },
    {
        "NAME": "MANIKANDAN SEENICHAMY",
        "GENDER": "M",
        "CITY": "PUNE",
        "STATE": "MAHARASHTRA",
        "NO. OF MARATHONS": 11,
        "STARS": "*",
        "YEAR": 2025
    },
    {
        "NAME": "MANJUNATH RAMAKRISHNA",
        "GENDER": "M",
        "CITY": "BENGALURU",
        "STATE": "KARNATAKA",
        "NO. OF MARATHONS": 11,
        "STARS": "*",
        "YEAR": 2025
    },
    {
        "NAME": "MOIZ RAJKOTWALA",
        "GENDER": "M",
        "CITY": "MUMBAI",
        "STATE": "MAHARASHTRA",
        "NO. OF MARATHONS": 11,
        "STARS": "*",
        "YEAR": 2025
    },
    {
        "NAME": "MONNAPPA BAYAVANDA",
        "GENDER": "M",
        "CITY": "BENGALURU",
        "STATE": "KARNATAKA",
        "NO. OF MARATHONS": 11,
        "STARS": "*",
        "YEAR": 2025
    },
    {
        "NAME": "NAVEENCHANDRA HEGDE",
        "GENDER": "M",
        "CITY": "MUMBAI",
        "STATE": "MAHARASHTRA",
        "NO. OF MARATHONS": 11,
        "STARS": "*",
        "YEAR": 2025
    },
    {
        "NAME": "NEVILLE FANIBANDA",
        "GENDER": "M",
        "CITY": "MUMBAI",
        "STATE": "MAHARASHTRA",
        "NO. OF MARATHONS": 11,
        "STARS": "*",
        "YEAR": 2025
    },
    {
        "NAME": "NITIN GAJAM",
        "GENDER": "M",
        "CITY": "MUMBAI",
        "STATE": "MAHARASHTRA",
        "NO. OF MARATHONS": 11,
        "STARS": "*",
        "YEAR": 2025
    },
    {
        "NAME": "NITIN PARMAR",
        "GENDER": "M",
        "CITY": "MUMBAI",
        "STATE": "MAHARASHTRA",
        "NO. OF MARATHONS": 11,
        "STARS": "*",
        "YEAR": 2025
    },
    {
        "NAME": "PANKAJ GUPTA",
        "GENDER": "M",
        "CITY": "MUMBAI",
        "STATE": "MAHARASHTRA",
        "NO. OF MARATHONS": 11,
        "STARS": "*",
        "YEAR": 2025
    },
    {
        "NAME": "PRADEEP KATRODIA",
        "GENDER": "M",
        "CITY": "MUMBAI",
        "STATE": "MAHARASHTRA",
        "NO. OF MARATHONS": 11,
        "STARS": "*",
        "YEAR": 2025
    },
    {
        "NAME": "RAJ KUMAR",
        "GENDER": "M",
        "CITY": "GHAZIABAD",
        "STATE": "UTTAR PRADESH",
        "NO. OF MARATHONS": 11,
        "STARS": "*",
        "YEAR": 2025
    },
    {
        "NAME": "RAM SHANKAR YADAV",
        "GENDER": "M",
        "CITY": "PUNE",
        "STATE": "MAHARASHTRA",
        "NO. OF MARATHONS": 11,
        "STARS": "*",
        "YEAR": 2025
    },
    {
        "NAME": "ROSHAN MORE",
        "GENDER": "M",
        "CITY": "MUMBAI",
        "STATE": "MAHARASHTRA",
        "NO. OF MARATHONS": 11,
        "STARS": "*",
        "YEAR": 2025
    },
    {
        "NAME": "SACHIN KUMBHAR",
        "GENDER": "M",
        "CITY": "NAVI MUMBAI",
        "STATE": "MAHARASHTRA",
        "NO. OF MARATHONS": 11,
        "STARS": "*",
        "YEAR": 2025
    },
    {
        "NAME": "SAGAR BHAT",
        "GENDER": "M",
        "CITY": "BENGALURU",
        "STATE": "KARNATAKA",
        "NO. OF MARATHONS": 11,
        "STARS": "*",
        "YEAR": 2025
    },
    {
        "NAME": "SAJIV KURUP",
        "GENDER": "M",
        "CITY": "NAVI MUMBAI",
        "STATE": "MAHARASHTRA",
        "NO. OF MARATHONS": 11,
        "STARS": "*",
        "YEAR": 2025
    },
    {
        "NAME": "SALIL CHUGH",
        "GENDER": "M",
        "CITY": "MUMBAI",
        "STATE": "MAHARASHTRA",
        "NO. OF MARATHONS": 11,
        "STARS": "*",
        "YEAR": 2025
    },
    {
        "NAME": "SANDEEP BHARGAVA",
        "GENDER": "M",
        "CITY": "NAVI MUMBAI",
        "STATE": "MAHARASHTRA",
        "NO. OF MARATHONS": 11,
        "STARS": "*",
        "YEAR": 2025
    },
    {
        "NAME": "SANDIP DHURI",
        "GENDER": "M",
        "CITY": "MUMBAI",
        "STATE": "MAHARASHTRA",
        "NO. OF MARATHONS": 11,
        "STARS": "*",
        "YEAR": 2025
    },
    {
        "NAME": "SATISH GUJARAN",
        "GENDER": "M",
        "CITY": "MUMBAI",
        "STATE": "MAHARASHTRA",
        "NO. OF MARATHONS": 11,
        "STARS": "*",
        "YEAR": 2025
    },
    {
        "NAME": "SATYA TRIPATHI",
        "GENDER": "M",
        "CITY": "NAVI MUMBAI",
        "STATE": "MAHARASHTRA",
        "NO. OF MARATHONS": 11,
        "STARS": "*",
        "YEAR": 2025
    },
    {
        "NAME": "SHIBANI GHARAT",
        "GENDER": "F",
        "CITY": "MUMBAI",
        "STATE": "MAHARASHTRA",
        "NO. OF MARATHONS": 11,
        "STARS": "*",
        "YEAR": 2025
    },
    {
        "NAME": "SHIRZAD KHORY",
        "GENDER": "M",
        "CITY": "MUMBAI",
        "STATE": "MAHARASHTRA",
        "NO. OF MARATHONS": 11,
        "STARS": "*",
        "YEAR": 2025
    },
    {
        "NAME": "SHRIPAD KULKARNI",
        "GENDER": "M",
        "CITY": "PUNE",
        "STATE": "MAHARASHTRA",
        "NO. OF MARATHONS": 11,
        "STARS": "*",
        "YEAR": 2025
    },
    {
        "NAME": "SHYAM KISHOR GOSWAMI",
        "GENDER": "M",
        "CITY": "DHANBAD",
        "STATE": "JHARKHAND",
        "NO. OF MARATHONS": 11,
        "STARS": "*",
        "YEAR": 2025
    },
    {
        "NAME": "SRINIVAS GEDDAM",
        "GENDER": "M",
        "CITY": "MUMBAI",
        "STATE": "MAHARASHTRA",
        "NO. OF MARATHONS": 11,
        "STARS": "*",
        "YEAR": 2025
    },
    {
        "NAME": "SRINIVAS VOORUVAKILI",
        "GENDER": "M",
        "CITY": "BENGALURU",
        "STATE": "KARNATAKA",
        "NO. OF MARATHONS": 11,
        "STARS": "*",
        "YEAR": 2025
    },
    {
        "NAME": "SUJIT KOLKE",
        "GENDER": "M",
        "CITY": "PUNE",
        "STATE": "MAHARASHTRA",
        "NO. OF MARATHONS": 11,
        "STARS": "*",
        "YEAR": 2025
    },
    {
        "NAME": "SURESH KANOJIA",
        "GENDER": "M",
        "CITY": "MUMBAI",
        "STATE": "MAHARASHTRA",
        "NO. OF MARATHONS": 11,
        "STARS": "*",
        "YEAR": 2025
    },
    {
        "NAME": "SURESH SESHADRI",
        "GENDER": "M",
        "CITY": "CHENNAI",
        "STATE": "TAMIL NADU",
        "NO. OF MARATHONS": 11,
        "STARS": "*",
        "YEAR": 2025
    },
    {
        "NAME": "THIRAVIARAJ NADAR",
        "GENDER": "M",
        "CITY": "THANE",
        "STATE": "MAHARASHTRA",
        "NO. OF MARATHONS": 11,
        "STARS": "*",
        "YEAR": 2025
    },
    {
        "NAME": "ULHAS SATHAYE",
        "GENDER": "M",
        "CITY": "JAMNAGAR",
        "STATE": "GUJARAT",
        "NO. OF MARATHONS": 11,
        "STARS": "*",
        "YEAR": 2025
    },
    {
        "NAME": "VEDANG MURTHY",
        "GENDER": "M",
        "CITY": "NAVI MUMBAI",
        "STATE": "MAHARASHTRA",
        "NO. OF MARATHONS": 11,
        "STARS": "*",
        "YEAR": 2025
    },
    {
        "NAME": "VIKAS DESHMUKH",
        "GENDER": "M",
        "CITY": "CHHATRAPATI SAMBHAJI NAGAR",
        "STATE": "MAHARASHTRA",
        "NO. OF MARATHONS": 11,
        "STARS": "*",
        "YEAR": 2025
    },
    {
        "NAME": "VINEET NANDAN GUPTA",
        "GENDER": "M",
        "CITY": "NAVI MUMBAI",
        "STATE": "MAHARASHTRA",
        "NO. OF MARATHONS": 11,
        "STARS": "*",
        "YEAR": 2025
    },
    {
        "NAME": "VISHAL KHATRY",
        "GENDER": "M",
        "CITY": "MUMBAI",
        "STATE": "MAHARASHTRA",
        "NO. OF MARATHONS": 11,
        "STARS": "*",
        "YEAR": 2025
    },
    {
        "NAME": "ABHISHEK SINGH",
        "GENDER": "M",
        "CITY": "NEW DELHI",
        "STATE": "DELHI",
        "NO. OF MARATHONS": 10,
        "STARS": "*",
        "YEAR": 2025
    },
    {
        "NAME": "AJAY RAO",
        "GENDER": "M",
        "CITY": "BENGALURU",
        "STATE": "KARNATAKA",
        "NO. OF MARATHONS": 10,
        "STARS": "*",
        "YEAR": 2025
    },
    {
        "NAME": "ALEX P JOB",
        "GENDER": "M",
        "CITY": "ERNAKULAM",
        "STATE": "KERALA",
        "NO. OF MARATHONS": 10,
        "STARS": "*",
        "YEAR": 2025
    },
    {
        "NAME": "AMITABH PRASAD",
        "GENDER": "M",
        "CITY": "PUNE",
        "STATE": "MAHARASHTRA",
        "NO. OF MARATHONS": 10,
        "STARS": "*",
        "YEAR": 2025
    },
    {
        "NAME": "AN SUBRAMANIAN",
        "GENDER": "M",
        "CITY": "BENGALURU",
        "STATE": "KARNATAKA",
        "NO. OF MARATHONS": 10,
        "STARS": "*",
        "YEAR": 2025
    },
    {
        "NAME": "ANAND PATIL",
        "GENDER": "M",
        "CITY": "MUMBAI",
        "STATE": "MAHARASHTRA",
        "NO. OF MARATHONS": 10,
        "STARS": "*",
        "YEAR": 2025
    },
    {
        "NAME": "ANAND SHARMA",
        "GENDER": "M",
        "CITY": "MUMBAI",
        "STATE": "MAHARASHTRA",
        "NO. OF MARATHONS": 10,
        "STARS": "*",
        "YEAR": 2025
    },
    {
        "NAME": "ANKUR BHATADA",
        "GENDER": "M",
        "CITY": "MUMBAI",
        "STATE": "MAHARASHTRA",
        "NO. OF MARATHONS": 10,
        "STARS": "*",
        "YEAR": 2025
    },
    {
        "NAME": "ARUN LONDHE",
        "GENDER": "M",
        "CITY": "PUNE",
        "STATE": "MAHARASHTRA",
        "NO. OF MARATHONS": 10,
        "STARS": "*",
        "YEAR": 2025
    },
    {
        "NAME": "ARUN VINOD KUMAR",
        "GENDER": "M",
        "CITY": "HYDERABAD",
        "STATE": "TELANGANA",
        "NO. OF MARATHONS": 10,
        "STARS": "*",
        "YEAR": 2025
    },
    {
        "NAME": "ASHOK KUMAR E R",
        "GENDER": "M",
        "CITY": "BENGALURU",
        "STATE": "KARNATAKA",
        "NO. OF MARATHONS": 10,
        "STARS": "*",
        "YEAR": 2025
    },
    {
        "NAME": "ATAULLA KHAN",
        "GENDER": "M",
        "CITY": "MUMBAI",
        "STATE": "MAHARASHTRA",
        "NO. OF MARATHONS": 10,
        "STARS": "*",
        "YEAR": 2025
    },
    {
        "NAME": "ATUL BHATIA",
        "GENDER": "M",
        "CITY": "MUMBAI",
        "STATE": "MAHARASHTRA",
        "NO. OF MARATHONS": 10,
        "STARS": "*",
        "YEAR": 2025
    },
    {
        "NAME": "AVINASH THAKUR DESAI",
        "GENDER": "M",
        "CITY": "MUMBAI",
        "STATE": "MAHARASHTRA",
        "NO. OF MARATHONS": 10,
        "STARS": "*",
        "YEAR": 2025
    },
    {
        "NAME": "AVNISH UPADHYAY",
        "GENDER": "M",
        "CITY": "PUNE",
        "STATE": "MAHARASHTRA",
        "NO. OF MARATHONS": 10,
        "STARS": "*",
        "YEAR": 2025
    },
    {
        "NAME": "BALKRISHNA SAPRE",
        "GENDER": "M",
        "CITY": "PUNE",
        "STATE": "MAHARASHTRA",
        "NO. OF MARATHONS": 10,
        "STARS": "*",
        "YEAR": 2025
    },
    {
        "NAME": "BHARATH AL",
        "GENDER": "M",
        "CITY": "BENGALURU",
        "STATE": "KARNATAKA",
        "NO. OF MARATHONS": 10,
        "STARS": "*",
        "YEAR": 2025
    },
    {
        "NAME": "BHOGENDRA MAHATO",
        "GENDER": "M",
        "CITY": "MUMBAI",
        "STATE": "MAHARASHTRA",
        "NO. OF MARATHONS": 10,
        "STARS": "*",
        "YEAR": 2025
    },
    {
        "NAME": "CARLYLE OLIVER",
        "GENDER": "M",
        "CITY": "MUMBAI",
        "STATE": "MAHARASHTRA",
        "NO. OF MARATHONS": 10,
        "STARS": "*",
        "YEAR": 2025
    },
    {
        "NAME": "CHANDRAKANT KOTIAN",
        "GENDER": "M",
        "CITY": "MUMBAI",
        "STATE": "MAHARASHTRA",
        "NO. OF MARATHONS": 10,
        "STARS": "*",
        "YEAR": 2025
    },
    {
        "NAME": "DEBASHIS SAHU",
        "GENDER": "M",
        "CITY": "MUMBAI",
        "STATE": "MAHARASHTRA",
        "NO. OF MARATHONS": 10,
        "STARS": "*",
        "YEAR": 2025
    },
    {
        "NAME": "DEV RAMAN",
        "GENDER": "M",
        "CITY": "MUMBAI",
        "STATE": "MAHARASHTRA",
        "NO. OF MARATHONS": 10,
        "STARS": "*",
        "YEAR": 2025
    },
    {
        "NAME": "DEVDATT KAWATHEKAR",
        "GENDER": "M",
        "CITY": "BENGALURU",
        "STATE": "KARNATAKA",
        "NO. OF MARATHONS": 10,
        "STARS": "*",
        "YEAR": 2025
    },
    {
        "NAME": "DEVEN LILANI",
        "GENDER": "M",
        "CITY": "MUMBAI",
        "STATE": "MAHARASHTRA",
        "NO. OF MARATHONS": 10,
        "STARS": "*",
        "YEAR": 2025
    },
    {
        "NAME": "FARID AHMED",
        "GENDER": "M",
        "CITY": "BENGALURU",
        "STATE": "KARNATAKA",
        "NO. OF MARATHONS": 10,
        "STARS": "*",
        "YEAR": 2025
    },
    {
        "NAME": "GAUTAM DAS",
        "GENDER": "M",
        "CITY": "MUMBAI",
        "STATE": "MAHARASHTRA",
        "NO. OF MARATHONS": 10,
        "STARS": "*",
        "YEAR": 2025
    },
    {
        "NAME": "GEORGE JOSEPH",
        "GENDER": "M",
        "CITY": "BENGALURU",
        "STATE": "KARNATAKA",
        "NO. OF MARATHONS": 10,
        "STARS": "*",
        "YEAR": 2025
    },
    {
        "NAME": "HARSHAD PENDSE",
        "GENDER": "M",
        "CITY": "PUNE",
        "STATE": "MAHARASHTRA",
        "NO. OF MARATHONS": 10,
        "STARS": "*",
        "YEAR": 2025
    },
    {
        "NAME": "HIMANSHU DHAR",
        "GENDER": "M",
        "CITY": "PUNE",
        "STATE": "MAHARASHTRA",
        "NO. OF MARATHONS": 10,
        "STARS": "*",
        "YEAR": 2025
    },
    {
        "NAME": "KAILAS SHINDE",
        "GENDER": "M",
        "CITY": "NAVI MUMBAI",
        "STATE": "MAHARASHTRA",
        "NO. OF MARATHONS": 10,
        "STARS": "*",
        "YEAR": 2025
    },
    {
        "NAME": "KASHISH PARIKH",
        "GENDER": "M",
        "CITY": "MUMBAI",
        "STATE": "MAHARASHTRA",
        "NO. OF MARATHONS": 10,
        "STARS": "*",
        "YEAR": 2025
    },
    {
        "NAME": "KESHAV SUSLADE",
        "GENDER": "M",
        "CITY": "THANE",
        "STATE": "MAHARASHTRA",
        "NO. OF MARATHONS": 10,
        "STARS": "*",
        "YEAR": 2025
    },
    {
        "NAME": "LEENESH BHULESCARR",
        "GENDER": "M",
        "CITY": "MUMBAI",
        "STATE": "MAHARASHTRA",
        "NO. OF MARATHONS": 10,
        "STARS": "*",
        "YEAR": 2025
    },
    {
        "NAME": "LITESH GADA",
        "GENDER": "M",
        "CITY": "MUMBAI",
        "STATE": "MAHARASHTRA",
        "NO. OF MARATHONS": 10,
        "STARS": "*",
        "YEAR": 2025
    },
    {
        "NAME": "MANOJ DESHPANDE",
        "GENDER": "M",
        "CITY": "PUNE",
        "STATE": "MAHARASHTRA",
        "NO. OF MARATHONS": 10,
        "STARS": "*",
        "YEAR": 2025
    },
    {
        "NAME": "MEHLAM FAIZULLABHOY",
        "GENDER": "M",
        "CITY": "MUMBAI",
        "STATE": "MAHARASHTRA",
        "NO. OF MARATHONS": 10,
        "STARS": "*",
        "YEAR": 2025
    },
    {
        "NAME": "MUKESH AGRAWAL",
        "GENDER": "M",
        "CITY": "BENGALURU",
        "STATE": "KARNATAKA",
        "NO. OF MARATHONS": 10,
        "STARS": "*",
        "YEAR": 2025
    },
    {
        "NAME": "MURTHY UDUPA",
        "GENDER": "M",
        "CITY": "BENGALURU",
        "STATE": "KARNATAKA",
        "NO. OF MARATHONS": 10,
        "STARS": "*",
        "YEAR": 2025
    },
    {
        "NAME": "NANDITA GANGWAL",
        "GENDER": "F",
        "CITY": "KOLKATA",
        "STATE": "WEST BENGAL",
        "NO. OF MARATHONS": 10,
        "STARS": "*",
        "YEAR": 2025
    },
    {
        "NAME": "NARENDER RAM",
        "GENDER": "M",
        "CITY": "NEW DELHI",
        "STATE": "DELHI",
        "NO. OF MARATHONS": 10,
        "STARS": "*",
        "YEAR": 2025
    },
    {
        "NAME": "NEERAJ MEHRA",
        "GENDER": "M",
        "CITY": "MUMBAI",
        "STATE": "MAHARASHTRA",
        "NO. OF MARATHONS": 10,
        "STARS": "*",
        "YEAR": 2025
    },
    {
        "NAME": "NIKHIL KALASKAR",
        "GENDER": "M",
        "CITY": "MUMBAI",
        "STATE": "MAHARASHTRA",
        "NO. OF MARATHONS": 10,
        "STARS": "*",
        "YEAR": 2025
    },
    {
        "NAME": "NIKHIL PEDNEKAR",
        "GENDER": "M",
        "CITY": "MUMBAI",
        "STATE": "MAHARASHTRA",
        "NO. OF MARATHONS": 10,
        "STARS": "*",
        "YEAR": 2025
    },
    {
        "NAME": "NIKUNJ KHEMANI",
        "GENDER": "M",
        "CITY": "MUMBAI",
        "STATE": "MAHARASHTRA",
        "NO. OF MARATHONS": 10,
        "STARS": "*",
        "YEAR": 2025
    },
    {
        "NAME": "NIRUPMA SINGH",
        "GENDER": "F",
        "CITY": "BENGALURU",
        "STATE": "KARNATAKA",
        "NO. OF MARATHONS": 10,
        "STARS": "*",
        "YEAR": 2025
    },
    {
        "NAME": "NITHIN DEVARAJAN",
        "GENDER": "M",
        "CITY": "BENGALURU",
        "STATE": "KARNATAKA",
        "NO. OF MARATHONS": 10,
        "STARS": "*",
        "YEAR": 2025
    },
    {
        "NAME": "PA MOHAMMED",
        "GENDER": "M",
        "CITY": "MANGALORE",
        "STATE": "KARNATAKA",
        "NO. OF MARATHONS": 10,
        "STARS": "*",
        "YEAR": 2025
    },
    {
        "NAME": "PARAG PENDHARKAR",
        "GENDER": "M",
        "CITY": "PUNE",
        "STATE": "MAHARASHTRA",
        "NO. OF MARATHONS": 10,
        "STARS": "*",
        "YEAR": 2025
    },
    {
        "NAME": "PINTO MANDAL",
        "GENDER": "M",
        "CITY": "MUMBAI",
        "STATE": "MAHARASHTRA",
        "NO. OF MARATHONS": 10,
        "STARS": "*",
        "YEAR": 2025
    },
    {
        "NAME": "POMESH MOMAYA",
        "GENDER": "M",
        "CITY": "MUMBAI",
        "STATE": "MAHARASHTRA",
        "NO. OF MARATHONS": 10,
        "STARS": "*",
        "YEAR": 2025
    },
    {
        "NAME": "POOJA SINGH",
        "GENDER": "F",
        "CITY": "SURAT",
        "STATE": "GUJARAT",
        "NO. OF MARATHONS": 10,
        "STARS": "*",
        "YEAR": 2025
    },
    {
        "NAME": "PRADEEP KADU",
        "GENDER": "M",
        "CITY": "MUMBAI",
        "STATE": "MAHARASHTRA",
        "NO. OF MARATHONS": 10,
        "STARS": "*",
        "YEAR": 2025
    },
    {
        "NAME": "PRAMOD SALVI",
        "GENDER": "M",
        "CITY": "MUMBAI",
        "STATE": "MAHARASHTRA",
        "NO. OF MARATHONS": 10,
        "STARS": "*",
        "YEAR": 2025
    },
    {
        "NAME": "PRASAD JADHAV",
        "GENDER": "M",
        "CITY": "KOLHAPUR",
        "STATE": "MAHARASHTRA",
        "NO. OF MARATHONS": 10,
        "STARS": "*",
        "YEAR": 2025
    },
    {
        "NAME": "PRASHANT GHOTIKAR",
        "GENDER": "M",
        "CITY": "MUMBAI",
        "STATE": "MAHARASHTRA",
        "NO. OF MARATHONS": 10,
        "STARS": "*",
        "YEAR": 2025
    },
    {
        "NAME": "PRATIK PARIKH",
        "GENDER": "M",
        "CITY": "MUMBAI",
        "STATE": "MAHARASHTRA",
        "NO. OF MARATHONS": 10,
        "STARS": "*",
        "YEAR": 2025
    },
    {
        "NAME": "PRAVEEN ARORA",
        "GENDER": "M",
        "CITY": "UDAIPUR",
        "STATE": "RAJASTHAN",
        "NO. OF MARATHONS": 10,
        "STARS": "*",
        "YEAR": 2025
    },
    {
        "NAME": "PRAVEEN KUMAR",
        "GENDER": "M",
        "CITY": "NAVI MUMBAI",
        "STATE": "MAHARASHTRA",
        "NO. OF MARATHONS": 10,
        "STARS": "*",
        "YEAR": 2025
    },
    {
        "NAME": "PREM KALLIATH",
        "GENDER": "M",
        "CITY": "MUMBAI",
        "STATE": "MAHARASHTRA",
        "NO. OF MARATHONS": 10,
        "STARS": "*",
        "YEAR": 2025
    },
    {
        "NAME": "PUSHPA BHATT",
        "GENDER": "F",
        "CITY": "MUMBAI",
        "STATE": "MAHARASHTRA",
        "NO. OF MARATHONS": 10,
        "STARS": "*",
        "YEAR": 2025
    },
    {
        "NAME": "RAJAN SHARMA",
        "GENDER": "M",
        "CITY": "MUMBAI",
        "STATE": "MAHARASHTRA",
        "NO. OF MARATHONS": 10,
        "STARS": "*",
        "YEAR": 2025
    },
    {
        "NAME": "RAJAN NAGDA",
        "GENDER": "M",
        "CITY": "MUMBAI",
        "STATE": "MAHARASHTRA",
        "NO. OF MARATHONS": 10,
        "STARS": "*",
        "YEAR": 2025
    },
    {
        "NAME": "RAJESH KARUVAT",
        "GENDER": "M",
        "CITY": "BENGALURU",
        "STATE": "KARNATAKA",
        "NO. OF MARATHONS": 10,
        "STARS": "*",
        "YEAR": 2025
    },
    {
        "NAME": "RAJESH PADHA",
        "GENDER": "M",
        "CITY": "JAMMU",
        "STATE": "JAMMU AND KASHMIR",
        "NO. OF MARATHONS": 10,
        "STARS": "*",
        "YEAR": 2025
    },
    {
        "NAME": "RAJESH WAGLE",
        "GENDER": "M",
        "CITY": "MUMBAI",
        "STATE": "MAHARASHTRA",
        "NO. OF MARATHONS": 10,
        "STARS": "*",
        "YEAR": 2025
    },
    {
        "NAME": "RAJESHA POOJARI",
        "GENDER": "M",
        "CITY": "MUMBAI",
        "STATE": "MAHARASHTRA",
        "NO. OF MARATHONS": 10,
        "STARS": "*",
        "YEAR": 2025
    },
    {
        "NAME": "RATAN DAVID",
        "GENDER": "M",
        "CITY": "MUMBAI",
        "STATE": "MAHARASHTRA",
        "NO. OF MARATHONS": 10,
        "STARS": "*",
        "YEAR": 2025
    },
    {
        "NAME": "RAVI KANDPAL",
        "GENDER": "M",
        "CITY": "MUMBAI",
        "STATE": "MAHARASHTRA",
        "NO. OF MARATHONS": 10,
        "STARS": "*",
        "YEAR": 2025
    },
    {
        "NAME": "RAVISH NARKAR",
        "GENDER": "M",
        "CITY": "MUMBAI",
        "STATE": "MAHARASHTRA",
        "NO. OF MARATHONS": 10,
        "STARS": "*",
        "YEAR": 2025
    },
    {
        "NAME": "RICHARD DSOUZA",
        "GENDER": "M",
        "CITY": "MUMBAI",
        "STATE": "MAHARASHTRA",
        "NO. OF MARATHONS": 10,
        "STARS": "*",
        "YEAR": 2025
    },
    {
        "NAME": "RITU RAJ TYAGI",
        "GENDER": "M",
        "CITY": "BENGALURU",
        "STATE": "KARNATAKA",
        "NO. OF MARATHONS": 10,
        "STARS": "*",
        "YEAR": 2025
    },
    {
        "NAME": "ROHAN ZAVERI",
        "GENDER": "M",
        "CITY": "MUMBAI",
        "STATE": "MAHARASHTRA",
        "NO. OF MARATHONS": 10,
        "STARS": "*",
        "YEAR": 2025
    },
    {
        "NAME": "ROHAN CHATURVEDI",
        "GENDER": "M",
        "CITY": "MUMBAI",
        "STATE": "MAHARASHTRA",
        "NO. OF MARATHONS": 10,
        "STARS": "*",
        "YEAR": 2025
    },
    {
        "NAME": "SACHIN NIJHAWAN",
        "GENDER": "M",
        "CITY": "MUMBAI",
        "STATE": "MAHARASHTRA",
        "NO. OF MARATHONS": 10,
        "STARS": "*",
        "YEAR": 2025
    },
    {
        "NAME": "SACHIN PALKAR",
        "GENDER": "M",
        "CITY": "MUMBAI",
        "STATE": "MAHARASHTRA",
        "NO. OF MARATHONS": 10,
        "STARS": "*",
        "YEAR": 2025
    },
    {
        "NAME": "SAMBANDAM DORAIVEL",
        "GENDER": "M",
        "CITY": "MUMBAI",
        "STATE": "MAHARASHTRA",
        "NO. OF MARATHONS": 10,
        "STARS": "*",
        "YEAR": 2025
    },
    {
        "NAME": "SAMIR CHAUDHARY",
        "GENDER": "M",
        "CITY": "BENGALURU",
        "STATE": "KARNATAKA",
        "NO. OF MARATHONS": 10,
        "STARS": "*",
        "YEAR": 2025
    },
    {
        "NAME": "SANDEEP LAXMAN",
        "GENDER": "M",
        "CITY": "MUMBAI",
        "STATE": "MAHARASHTRA",
        "NO. OF MARATHONS": 10,
        "STARS": "*",
        "YEAR": 2025
    },
    {
        "NAME": "SANDESH SANKHE",
        "GENDER": "M",
        "CITY": "MUMBAI",
        "STATE": "MAHARASHTRA",
        "NO. OF MARATHONS": 10,
        "STARS": "*",
        "YEAR": 2025
    },
    {
        "NAME": "SANTOSH THOURANI",
        "GENDER": "M",
        "CITY": "MUMBAI",
        "STATE": "MAHARASHTRA",
        "NO. OF MARATHONS": 10,
        "STARS": "*",
        "YEAR": 2025
    },
    {
        "NAME": "SANTOSH ZURANGE",
        "GENDER": "M",
        "CITY": "PUNE",
        "STATE": "MAHARASHTRA",
        "NO. OF MARATHONS": 10,
        "STARS": "*",
        "YEAR": 2025
    },
    {
        "NAME": "SAURABH GARG",
        "GENDER": "M",
        "CITY": "NEW DELHI",
        "STATE": "DELHI",
        "NO. OF MARATHONS": 10,
        "STARS": "*",
        "YEAR": 2025
    },
    {
        "NAME": "SHAILENDRA JAHAGIRDAR",
        "GENDER": "M",
        "CITY": "MUMBAI",
        "STATE": "MAHARASHTRA",
        "NO. OF MARATHONS": 10,
        "STARS": "*",
        "YEAR": 2025
    },
    {
        "NAME": "SHARAD SAXENA",
        "GENDER": "M",
        "CITY": "NAVI MUMBAI",
        "STATE": "MAHARASHTRA",
        "NO. OF MARATHONS": 10,
        "STARS": "*",
        "YEAR": 2025
    },
    {
        "NAME": "SIVABALAN PANDIAN",
        "GENDER": "M",
        "CITY": "MUMBAI",
        "STATE": "MAHARASHTRA",
        "NO. OF MARATHONS": 10,
        "STARS": "*",
        "YEAR": 2025
    },
    {
        "NAME": "SIVAKUMAR POTNURU",
        "GENDER": "M",
        "CITY": "HYDERABAD",
        "STATE": "TELANGANA",
        "NO. OF MARATHONS": 10,
        "STARS": "*",
        "YEAR": 2025
    },
    {
        "NAME": "SREEGITH NAIR",
        "GENDER": "M",
        "CITY": "NAVI MUMBAI",
        "STATE": "MAHARASHTRA",
        "NO. OF MARATHONS": 10,
        "STARS": "*",
        "YEAR": 2025
    },
    {
        "NAME": "SUBODH CHAVAN",
        "GENDER": "M",
        "CITY": "THANE",
        "STATE": "MAHARASHTRA",
        "NO. OF MARATHONS": 10,
        "STARS": "*",
        "YEAR": 2025
    },
    {
        "NAME": "SUMANT KUMAR",
        "GENDER": "M",
        "CITY": "NEW DELHI",
        "STATE": "DELHI",
        "NO. OF MARATHONS": 10,
        "STARS": "*",
        "YEAR": 2025
    },
    {
        "NAME": "SUMIT SHAH",
        "GENDER": "M",
        "CITY": "NAINITAL",
        "STATE": "UTTARAKHAND",
        "NO. OF MARATHONS": 10,
        "STARS": "*",
        "YEAR": 2025
    },
    {
        "NAME": "SUNDARESAN RENGANATHAN",
        "GENDER": "M",
        "CITY": "NAVI MUMBAI",
        "STATE": "MAHARASHTRA",
        "NO. OF MARATHONS": 10,
        "STARS": "*",
        "YEAR": 2025
    },
    {
        "NAME": "SUNIL SHETTY",
        "GENDER": "M",
        "CITY": "MUMBAI",
        "STATE": "MAHARASHTRA",
        "NO. OF MARATHONS": 10,
        "STARS": "*",
        "YEAR": 2025
    },
    {
        "NAME": "SUNIL HANDA",
        "GENDER": "M",
        "CITY": "KARWAR",
        "STATE": "KARNATAKA",
        "NO. OF MARATHONS": 10,
        "STARS": "*",
        "YEAR": 2025
    },
    {
        "NAME": "SURESH SHIVARAM",
        "GENDER": "M",
        "CITY": "MUMBAI",
        "STATE": "MAHARASHTRA",
        "NO. OF MARATHONS": 10,
        "STARS": "*",
        "YEAR": 2025
    },
    {
        "NAME": "SURESH CHETWANI",
        "GENDER": "M",
        "CITY": "BENGALURU",
        "STATE": "KARNATAKA",
        "NO. OF MARATHONS": 10,
        "STARS": "*",
        "YEAR": 2025
    },
    {
        "NAME": "SURESH GAVIT",
        "GENDER": "M",
        "CITY": "RATNAGIRI",
        "STATE": "MAHARASHTRA",
        "NO. OF MARATHONS": 10,
        "STARS": "*",
        "YEAR": 2025
    },
    {
        "NAME": "SUSHANT KARKERA",
        "GENDER": "M",
        "CITY": "MUMBAI",
        "STATE": "MAHARASHTRA",
        "NO. OF MARATHONS": 10,
        "STARS": "*",
        "YEAR": 2025
    },
    {
        "NAME": "SWAPNIL MHATRE",
        "GENDER": "M",
        "CITY": "MUMBAI",
        "STATE": "MAHARASHTRA",
        "NO. OF MARATHONS": 10,
        "STARS": "*",
        "YEAR": 2025
    },
    {
        "NAME": "UDAYA KUMAR",
        "GENDER": "M",
        "CITY": "BENGALURU",
        "STATE": "KARNATAKA",
        "NO. OF MARATHONS": 10,
        "STARS": "*",
        "YEAR": 2025
    },
    {
        "NAME": "VANDANA PAREKH",
        "GENDER": "F",
        "CITY": "MUMBAI",
        "STATE": "MAHARASHTRA",
        "NO. OF MARATHONS": 10,
        "STARS": "*",
        "YEAR": 2025
    },
    {
        "NAME": "VARKEY JOSEPH",
        "GENDER": "M",
        "CITY": "MUMBAI",
        "STATE": "MAHARASHTRA",
        "NO. OF MARATHONS": 10,
        "STARS": "*",
        "YEAR": 2025
    },
    {
        "NAME": "VIJAY BABBAR",
        "GENDER": "M",
        "CITY": "GURGAON",
        "STATE": "HARYANA",
        "NO. OF MARATHONS": 10,
        "STARS": "*",
        "YEAR": 2025
    },
    {
        "NAME": "VIKAS MALPUTE",
        "GENDER": "M",
        "CITY": "PUNE",
        "STATE": "MAHARASHTRA",
        "NO. OF MARATHONS": 10,
        "STARS": "*",
        "YEAR": 2025
    },
    {
        "NAME": "VINAYAK ZAMBRE",
        "GENDER": "M",
        "CITY": "MUMBAI",
        "STATE": "MAHARASHTRA",
        "NO. OF MARATHONS": 10,
        "STARS": "*",
        "YEAR": 2025
    },
    {
        "NAME": "VINEET AGARWAL",
        "GENDER": "M",
        "CITY": "GURGAON",
        "STATE": "HARYANA",
        "NO. OF MARATHONS": 10,
        "STARS": "*",
        "YEAR": 2025
    },
    {
        "NAME": "VINOD KAUL",
        "GENDER": "M",
        "CITY": "GURGAON",
        "STATE": "HARYANA",
        "NO. OF MARATHONS": 10,
        "STARS": "*",
        "YEAR": 2025
    },
    {
        "NAME": "VISHAL DUA",
        "GENDER": "M",
        "CITY": "NEW DELHI",
        "STATE": "DELHI",
        "NO. OF MARATHONS": 10,
        "STARS": "*",
        "YEAR": 2025
    },
    {
        "NAME": "VISHAL SAROHA",
        "GENDER": "M",
        "CITY": "PUNE",
        "STATE": "MAHARASHTRA",
        "NO. OF MARATHONS": 10,
        "STARS": "*",
        "YEAR": 2025
    },
    {
        "NAME": "VISHWANATH SHETYE",
        "GENDER": "M",
        "CITY": "VASCO",
        "STATE": "GOA",
        "NO. OF MARATHONS": 10,
        "STARS": "*",
        "YEAR": 2025
    },
    {
        "NAME": "VIVEK PRASAD",
        "GENDER": "M",
        "CITY": "PUNE",
        "STATE": "MAHARASHTRA",
        "NO. OF MARATHONS": 10,
        "STARS": "*",
        "YEAR": 2025
    },
    {
        "NAME": "VIVEK SHUKLA",
        "GENDER": "M",
        "CITY": "THANE",
        "STATE": "MAHARASHTRA",
        "NO. OF MARATHONS": 10,
        "STARS": "*",
        "YEAR": 2025
    },
    {
        "NAME": "VIVEK BHARGAVA",
        "GENDER": "M",
        "CITY": "PUNE",
        "STATE": "MAHARASHTRA",
        "NO. OF MARATHONS": 10,
        "STARS": "*",
        "YEAR": 2025
    },
    {
        "NAME": "VYANKATESH BENDRE",
        "GENDER": "M",
        "CITY": "THANE",
        "STATE": "MAHARASHTRA",
        "NO. OF MARATHONS": 10,
        "STARS": "*",
        "YEAR": 2025
    },
    {
        "NAME": "YOGESH CHAVAN",
        "GENDER": "M",
        "CITY": "MUMBAI",
        "STATE": "MAHARASHTRA",
        "NO. OF MARATHONS": 10,
        "STARS": "*",
        "YEAR": 2025
    },
    {
        "NAME": "YOGESH RAWAT",
        "GENDER": "M",
        "CITY": "NOIDA",
        "STATE": "UTTAR PRADESH",
        "NO. OF MARATHONS": 10,
        "STARS": "*",
        "YEAR": 2025
    }
]